grou/__init__.py
grou/command_line.py
grou/common.py
grou/git_info_converter.py
grou/grou.py
grou/grou_main.py
grou/merge_info_converter.py
grou/merge_info_formatter.py
grou-0.1.6.dist-info/LICENSE
grou-0.1.6.dist-info/METADATA
grou-0.1.6.dist-info/WHEEL
grou-0.1.6.dist-info/entry_points.txt
grou-0.1.6.dist-info/top_level.txt
grou-0.1.6.dist-info/RECORD
