Metadata-Version: 2.1
Name: grou
Version: 0.1.6
Summary: grou stands for Git Release note OUtput command.
Requires-Dist: enum34
Requires-Dist: future
